chalkharness/__init__.py
chalkharness/py.typed
chalk_harness-1.31.2.dist-info/METADATA
chalk_harness-1.31.2.dist-info/WHEEL
chalk_harness-1.31.2.dist-info/top_level.txt
chalk_harness-1.31.2.dist-info/RECORD
