Metadata-Version: 2.1
Name: chalk-harness
Version: 1.31.2
Summary: Python wrapper for Chalk's CLI
Home-page: https://chalk.ai
Author: Chalk AI, Inc.
Classifier: Programming Language :: Python
Classifier: Programming Language :: Python :: 3
Classifier: Programming Language :: Python :: 3.8
Requires-Python: >=3.8.0
Requires-Dist: pydantic>=1.0.0
